{
    "adventure stories": 0,
    "african american & black": 1,
    "alphabet": 2,
    "architecture": 3,
    "art & music": 4,
    "asian american & pacific islander": 5,
    "baby animals": 6,
    "basketball": 7,
    "bedtime stories": 8,
    "biography & memoir": 9,
    "birds": 10,
    "books & libraries": 11,
    "boys & men": 12,
    "bullying": 13,
    "cats": 14,
    "christmas": 15,
    "city life": 16,
    "classics": 17,
    "colors": 18,
    "coming of age": 19,
    "computers": 20,
    "counting & numbers": 21,
    "country life": 22,
    "crafts & hobbies": 23,
    "curiosities & wonders": 24,
    "disabilities": 25,
    "diversity & multicultural": 26,
    "dogs": 27,
    "dreams & imagination": 28,
    "early concepts": 29,
    "emotions & feelings": 30,
    "environment": 31,
    "fables": 32,
    "fairy tales & folktales": 33,
    "family & friends": 34,
    "fantasy": 35,
    "farm animals": 36,
    "farm life": 37,
    "fitness": 38,
    "food": 39,
    "football": 40,
    "fun science": 41,
    "funny comics": 42,
    "funny poems": 43,
    "funny stories": 44,
    "games & activities": 45,
    "getting dressed": 46,
    "girls & women": 47,
    "healthy habits": 48,
    "hispanic & latino": 49,
    "historical fiction": 50,
    "history": 51,
    "history of america": 52,
    "holidays & celebrations": 53,
    "immigration": 54,
    "indigenous": 55,
    "jokes & riddles": 56,
    "language arts": 57,
    "law & crime": 58,
    "legends": 59,
    "lgbtq+": 60,
    "loss & grief": 61,
    "magic & myth": 62,
    "manners": 63,
    "math": 64,
    "mental health": 65,
    "mermaids": 66,
    "mindfulness": 67,
    "mystery stories": 68,
    "mythical creatures": 69,
    "mythology": 70,
    "myths": 71,
    "native american": 72,
    "occupations": 73,
    "our friends in nature": 74,
    "pets": 75,
    "philosophy": 76,
    "pirates": 77,
    "places": 78,
    "places of interest": 79,
    "rabbits": 80,
    "reimagined tales": 81,
    "religion": 82,
    "religious": 83,
    "royal families": 84,
    "royalty": 85,
    "school & education": 86,
    "science & exploration": 87,
    "science fiction": 88,
    "seasons": 89,
    "social studies": 90,
    "social topics": 91,
    "space exploration": 92,
    "spies & assassins": 93,
    "spooky stories": 94,
    "sports & games": 95,
    "superheroes": 96,
    "technology": 97,
    "the natural world": 98,
    "transportation": 99,
    "travel": 100,
    "values & virtues": 101,
    "visionary & metaphysical": 102,
    "werewolves": 103,
    "westerns": 104,
    "wild animals": 105,
    "zombies": 106,
    "unk": 107
}